lit_sandbox/__about__.py
lit_sandbox/__init__.py
lit_sandbox/my_module.py
thunderjit-0.0.0.dev0.dist-info/LICENSE
thunderjit-0.0.0.dev0.dist-info/METADATA
thunderjit-0.0.0.dev0.dist-info/WHEEL
thunderjit-0.0.0.dev0.dist-info/top_level.txt
thunderjit-0.0.0.dev0.dist-info/RECORD
