Metadata-Version: 2.1
Name: thunderjit
Version: 0.0.0.dev0
Summary: PyTorch Lightning Sample project.
Home-page: https://github.com/Lightning-AI/lightning-sandbox
Download-URL: https://github.com/Lightning-AI/lightning-sandbox
Author: Lightning-AI et al.
Author-email: community@lightning.ai
License: Apache-2.0
Project-URL: Bug Tracker, https://github.com/Lightning-AI/lightning-sandbox/issues
Project-URL: Documentation, https://lightning-ai.github.io/lightning-sandbox/
Project-URL: Source Code, https://github.com/Lightning-AI/lightning-sandbox
Keywords: deep learning,pytorch,AI
Classifier: Environment :: Console
Classifier: Natural Language :: English
Classifier: Development Status :: 3 - Alpha
Classifier: Intended Audience :: Developers
Classifier: Topic :: Scientific/Engineering :: Artificial Intelligence
Classifier: Topic :: Scientific/Engineering :: Information Analysis
Classifier: License :: OSI Approved :: Apache Software License
Classifier: Operating System :: OS Independent
Classifier: Programming Language :: Python :: 3
Classifier: Programming Language :: Python :: 3.8
Classifier: Programming Language :: Python :: 3.9
Classifier: Programming Language :: Python :: 3.10
Classifier: Programming Language :: Python :: 3.11
Requires-Python: >=3.8
License-File: LICENSE
Requires-Dist: torch >=2.0.0
Requires-Dist: lightning >=2.0.0
Provides-Extra: test
Requires-Dist: coverage >=5.0 ; extra == 'test'
Requires-Dist: mypy ==1.8.0 ; extra == 'test'
Requires-Dist: pytest-cov ; extra == 'test'
Requires-Dist: pytest >=6.0 ; extra == 'test'
